[{
  "@context": "https://www.w3.org/ns/did/v1",
  "id": "did:example:123456789abcdefghi",
  "authentication": [{
    "id": "did:example:123456789abcdefghi#keys-1",
    "type": "RsaVerificationKey2018",
    "controller": "did:example:123456789abcdefghi",
    "publicKeyPem": "-----BEGIN PUBLIC KEY...END PUBLIC KEY-----\r\n"
  }],
  "jurisdictionMetadata": {
    "jurisdictionName": "United Kingdom",
    "jurisdictionAddr": "0x123456789abcdefghi",
    "ISO3": "GBR",
    "borders": null
  },
  "service": [{
      "id": "did:example:123456789abcdefghi#london-congestion-zone",
      "name": "London Congestion Zone",
      "zoneType": ["urban", "road"],
      "serviceEndpoint": "https://raw.githubusercontent.com/johnx25bd/LBL-FutureOfBlockchain2020/fetch-geometries/data/zones/london-congestion-zone.json",
      "policies": {
        "beneficiary": "0x456789123cdef",
        "chargePerMinute": 0.15,
        "currency": "GBP"
      }
    },
    {
      "id": "did:example:123456789abcdefghi#heathrow-restricted-airspace",
      "name": "Heathrow Restricted Airspace",
      "zoneType": ["urban", "aerial"],
      "serviceEndpoint": "https://raw.githubusercontent.com/johnx25bd/LBL-FutureOfBlockchain2020/fetch-geometries/data/zones/heathrow-restricted-airspace.json",
      "policies": {
        "beneficiary": "0x678912345fghi...",
        "chargePerMinute": 0,
        "currency": "GBP"
      }
    },
    {
      "id": "did:example:123456789abcdefghi#port-of-southampton",
      "zoneType": ["port", "maritime"],
      "name": "Port of Southampton",
      "serviceEndpoint": "https://raw.githubusercontent.com/johnx25bd/LBL-FutureOfBlockchain2020/fetch-geometries/data/zones/port-of-southampton.json",
      "policies": {
        "beneficiary": "0x89123456efghi...",
        "chargePerMinute": 0,
        "currency": "GBP"
      }
    }
  ]
}
]
